{
  "meta": {
    "scope": "state_house",
    "contest_type": "attorney_general",
    "year": 2022,
    "method": "block_assignment_vtd_population_weighted",
    "crosswalk_files_available": [
      "nhgis_blk2000_blk2010_48.zip",
      "nhgis_blk2010_blk2020_48.zip",
      "nhgis_blk2020_blk2010_48.zip"
    ],
    "match_coverage_pct": 83.43864426509793,
    "matched_precinct_rows": 5057,
    "total_precinct_rows": 5948,
    "matched_total_votes": 4013962,
    "total_votes": 4810675,
    "generated_at": "2026-03-03T22:22:49.419915+00:00"
  },
  "general": {
    "results": {
      "1": {
        "dem_votes": 7520,
        "rep_votes": 30303,
        "other_votes": 978,
        "total_votes": 38801,
        "dem_candidate": "Rochelle Mercedes Garza",
        "rep_candidate": "Ken Paxton",
        "margin": 22783,
        "margin_pct": 58.717558825803465,
        "winner": "REP"
      },
      "3": {
        "dem_votes": 9842,
        "rep_votes": 40891,
        "other_votes": 1178,
        "total_votes": 51911,
        "dem_candidate": "Rochelle Mercedes Garza",
        "rep_candidate": "Ken Paxton",
        "margin": 31049,
        "margin_pct": 59.811985898942424,
        "winner": "REP"
      },
      "4": {
        "dem_votes": 12628,
        "rep_votes": 33838,
        "other_votes": 1699,
        "total_votes": 48165,
        "dem_candidate": "Rochelle Mercedes Garza",
        "rep_candidate": "Ken Paxton",
        "margin": 21210,
        "margin_pct": 44.03612581750234,
        "winner": "REP"
      },
      "5": {
        "dem_votes": 3447,
        "rep_votes": 15196,
        "other_votes": 538,
        "total_votes": 19181,
        "dem_candidate": "Rochelle Mercedes Garza",
        "rep_candidate": "Ken Paxton",
        "margin": 11749,
        "margin_pct": 61.25332360148064,
        "winner": "REP"
      },
      "6": {
        "dem_votes": 14542,
        "rep_votes": 35911,
        "other_votes": 1973,
        "total_votes": 52426,
        "dem_candidate": "Rochelle Mercedes Garza",
        "rep_candidate": "Ken Paxton",
        "margin": 21369,
        "margin_pct": 40.76030976996147,
        "winner": "REP"
      },
      "7": {
        "dem_votes": 8793,
        "rep_votes": 23463,
        "other_votes": 719,
        "total_votes": 32975,
        "dem_candidate": "ROCHELLE MERCEDES GARZA",
        "rep_candidate": "KEN PAXTON",
        "margin": 14670,
        "margin_pct": 44.4882486732373,
        "winner": "REP"
      },
      "8": {
        "dem_votes": 3199,
        "rep_votes": 14624,
        "other_votes": 390,
        "total_votes": 18213,
        "dem_candidate": "Rochelle Mercedes Garza",
        "rep_candidate": "Ken Paxton",
        "margin": 11425,
        "margin_pct": 62.72991819030362,
        "winner": "REP"
      },
      "9": {
        "dem_votes": 407,
        "rep_votes": 3725,
        "other_votes": 34,
        "total_votes": 4166,
        "dem_candidate": "Rochelle Mercedes Garza",
        "rep_candidate": "Ken Paxton",
        "margin": 3318,
        "margin_pct": 79.64474315890543,
        "winner": "REP"
      },
      "10": {
        "dem_votes": 815,
        "rep_votes": 3601,
        "other_votes": 184,
        "total_votes": 4600,
        "dem_candidate": "Rochelle Mercedes Garza",
        "rep_candidate": "Ken Paxton",
        "margin": 2786,
        "margin_pct": 60.56521739130435,
        "winner": "REP"
      },
      "11": {
        "dem_votes": 5446,
        "rep_votes": 12918,
        "other_votes": 469,
        "total_votes": 18833,
        "dem_candidate": "Rochelle Mercedes Garza",
        "rep_candidate": "Ken Paxton",
        "margin": 7472,
        "margin_pct": 39.67503849625657,
        "winner": "REP"
      },
      "12": {
        "dem_votes": 11496,
        "rep_votes": 28002,
        "other_votes": 3882,
        "total_votes": 43380,
        "dem_candidate": "Rochelle Mercedes Garza",
        "rep_candidate": "Ken Paxton",
        "margin": 16506,
        "margin_pct": 38.05038084542991,
        "winner": "REP"
      },
      "13": {
        "dem_votes": 5345,
        "rep_votes": 22279,
        "other_votes": 1201,
        "total_votes": 28825,
        "dem_candidate": "Rochelle Mercedes Garza",
        "rep_candidate": "Ken Paxton",
        "margin": 16934,
        "margin_pct": 58.74761491760625,
        "winner": "REP"
      },
      "14": {
        "dem_votes": 15795,
        "rep_votes": 19198,
        "other_votes": 1405,
        "total_votes": 36398,
        "dem_candidate": "Rochelle Mercedes Garza",
        "rep_candidate": "Ken Paxton",
        "margin": 3403,
        "margin_pct": 9.348949537445604,
        "winner": "REP"
      },
      "15": {
        "dem_votes": 25899,
        "rep_votes": 49456,
        "other_votes": 2225,
        "total_votes": 77580,
        "dem_candidate": "Rochelle Mercedes Garza",
        "rep_candidate": "Ken Paxton",
        "margin": 23557,
        "margin_pct": 30.36478473833462,
        "winner": "REP"
      },
      "16": {
        "dem_votes": 12176,
        "rep_votes": 47946,
        "other_votes": 1503,
        "total_votes": 61625,
        "dem_candidate": "Rochelle Mercedes Garza",
        "rep_candidate": "Ken Paxton",
        "margin": 35770,
        "margin_pct": 58.0446247464503,
        "winner": "REP"
      },
      "17": {
        "dem_votes": 7610,
        "rep_votes": 9185,
        "other_votes": 4508,
        "total_votes": 21303,
        "dem_candidate": "Rochelle Mercedes Garza",
        "rep_candidate": "Ken Paxton",
        "margin": 1575,
        "margin_pct": 7.39332488381918,
        "winner": "REP"
      },
      "18": {
        "dem_votes": 1394,
        "rep_votes": 7208,
        "other_votes": 177,
        "total_votes": 8779,
        "dem_candidate": "Rochelle Mercedes Garza",
        "rep_candidate": "Ken Paxton",
        "margin": 5814,
        "margin_pct": 66.22622166533773,
        "winner": "REP"
      },
      "20": {
        "dem_votes": 18466,
        "rep_votes": 40358,
        "other_votes": 3436,
        "total_votes": 62261,
        "dem_candidate": "Rochelle Mercedes Garza",
        "rep_candidate": "Ken Paxton",
        "margin": 21892,
        "margin_pct": 35.16231807825757,
        "winner": "REP"
      },
      "21": {
        "dem_votes": 9934,
        "rep_votes": 42436,
        "other_votes": 1547,
        "total_votes": 53917,
        "dem_candidate": "Rochelle Mercedes Garza",
        "rep_candidate": "Ken Paxton",
        "margin": 32502,
        "margin_pct": 60.281543854442944,
        "winner": "REP"
      },
      "22": {
        "dem_votes": 20542,
        "rep_votes": 12482,
        "other_votes": 1187,
        "total_votes": 34211,
        "dem_candidate": "Rochelle Mercedes Garza",
        "rep_candidate": "Ken Paxton",
        "margin": -8060,
        "margin_pct": -23.55967378913215,
        "winner": "DEM"
      },
      "25": {
        "dem_votes": 9973,
        "rep_votes": 26174,
        "other_votes": 1157,
        "total_votes": 37304,
        "dem_candidate": "Rochelle Mercedes Garza",
        "rep_candidate": "Ken Paxton",
        "margin": 16201,
        "margin_pct": 43.4296590177997,
        "winner": "REP"
      },
      "26": {
        "dem_votes": 3411,
        "rep_votes": 3990,
        "other_votes": 217,
        "total_votes": 7618,
        "dem_candidate": "Rochelle Mercedes Garza",
        "rep_candidate": "Ken Paxton",
        "margin": 579,
        "margin_pct": 7.600420057757942,
        "winner": "REP"
      },
      "27": {
        "dem_votes": 21558,
        "rep_votes": 5093,
        "other_votes": 637,
        "total_votes": 27288,
        "dem_candidate": "Rochelle Mercedes Garza",
        "rep_candidate": "Ken Paxton",
        "margin": -16465,
        "margin_pct": -60.3378774552917,
        "winner": "DEM"
      },
      "28": {
        "dem_votes": 2325,
        "rep_votes": 3004,
        "other_votes": 158,
        "total_votes": 5487,
        "dem_candidate": "Rochelle Mercedes Garza",
        "rep_candidate": "Ken Paxton",
        "margin": 679,
        "margin_pct": 12.374703845452888,
        "winner": "REP"
      },
      "29": {
        "dem_votes": 26582,
        "rep_votes": 31063,
        "other_votes": 1608,
        "total_votes": 59253,
        "dem_candidate": "Rochelle Mercedes Garza",
        "rep_candidate": "Ken Paxton",
        "margin": 4481,
        "margin_pct": 7.562486287614129,
        "winner": "REP"
      },
      "30": {
        "dem_votes": 4688,
        "rep_votes": 15545,
        "other_votes": 830,
        "total_votes": 21063,
        "dem_candidate": "Rochelle Mercedes Garza",
        "rep_candidate": "Ken Paxton",
        "margin": 10857,
        "margin_pct": 51.54536390827518,
        "winner": "REP"
      },
      "31": {
        "dem_votes": 4897,
        "rep_votes": 9273,
        "other_votes": 602,
        "total_votes": 14772,
        "dem_candidate": "Rochelle Mercedes Garza",
        "rep_candidate": "Ken Paxton",
        "margin": 4376,
        "margin_pct": 29.623612239371784,
        "winner": "REP"
      },
      "32": {
        "dem_votes": 20934,
        "rep_votes": 26870,
        "other_votes": 1307,
        "total_votes": 49111,
        "dem_candidate": "Rochelle Mercedes Garza",
        "rep_candidate": "Ken Paxton",
        "margin": 5936,
        "margin_pct": 12.086905173993607,
        "winner": "REP"
      },
      "33": {
        "dem_votes": 29632,
        "rep_votes": 50875,
        "other_votes": 3552,
        "total_votes": 84059,
        "dem_candidate": "Rochelle Mercedes Garza",
        "rep_candidate": "Ken Paxton",
        "margin": 21243,
        "margin_pct": 25.271535469134776,
        "winner": "REP"
      },
      "34": {
        "dem_votes": 18709,
        "rep_votes": 18459,
        "other_votes": 778,
        "total_votes": 37946,
        "dem_candidate": "Rochelle Mercedes Garza",
        "rep_candidate": "Ken Paxton",
        "margin": -250,
        "margin_pct": -0.6588309703262532,
        "winner": "DEM"
      },
      "35": {
        "dem_votes": 6798,
        "rep_votes": 6823,
        "other_votes": 647,
        "total_votes": 14268,
        "dem_candidate": "Rochelle Mercedes Garza",
        "rep_candidate": "Ken Paxton",
        "margin": 25,
        "margin_pct": 0.17521726941407345,
        "winner": "REP"
      },
      "37": {
        "dem_votes": 16600,
        "rep_votes": 11850,
        "other_votes": 1663,
        "total_votes": 30113,
        "dem_candidate": "Rochelle Mercedes Garza",
        "rep_candidate": "Ken Paxton",
        "margin": -4750,
        "margin_pct": -15.773918241291138,
        "winner": "DEM"
      },
      "38": {
        "dem_votes": 17355,
        "rep_votes": 13109,
        "other_votes": 1520,
        "total_votes": 31984,
        "dem_candidate": "Rochelle Mercedes Garza",
        "rep_candidate": "Ken Paxton",
        "margin": -4246,
        "margin_pct": -13.275387693846923,
        "winner": "DEM"
      },
      "43": {
        "dem_votes": 7769,
        "rep_votes": 15781,
        "other_votes": 497,
        "total_votes": 24047,
        "dem_candidate": "Rochelle Mercedes Garza",
        "rep_candidate": "Ken Paxton",
        "margin": 8012,
        "margin_pct": 33.318085416060214,
        "winner": "REP"
      },
      "44": {
        "dem_votes": 17884,
        "rep_votes": 41577,
        "other_votes": 2668,
        "total_votes": 62129,
        "dem_candidate": "Rochelle Mercedes Garza",
        "rep_candidate": "Ken Paxton",
        "margin": 23693,
        "margin_pct": 38.13517037132418,
        "winner": "REP"
      },
      "45": {
        "dem_votes": 19788,
        "rep_votes": 14540,
        "other_votes": 1161,
        "total_votes": 35489,
        "dem_candidate": "Rochelle Mercedes Garza",
        "rep_candidate": "Ken Paxton",
        "margin": -5248,
        "margin_pct": -14.787680689791202,
        "winner": "DEM"
      },
      "52": {
        "dem_votes": 20228,
        "rep_votes": 17797,
        "other_votes": 2915,
        "total_votes": 40939,
        "dem_candidate": "Rochelle Mercedes Garza",
        "rep_candidate": "Ken Paxton",
        "margin": -2431,
        "margin_pct": -5.938747532389678,
        "winner": "DEM"
      },
      "53": {
        "dem_votes": 8645,
        "rep_votes": 34722,
        "other_votes": 7519,
        "total_votes": 50886,
        "dem_candidate": "Rochelle Mercedes Garza",
        "rep_candidate": "Ken Paxton",
        "margin": 26077,
        "margin_pct": 51.24592225759541,
        "winner": "REP"
      },
      "54": {
        "dem_votes": 16354,
        "rep_votes": 19984,
        "other_votes": 1254,
        "total_votes": 37592,
        "dem_candidate": "Rochelle Mercedes Garza",
        "rep_candidate": "Ken Paxton",
        "margin": 3630,
        "margin_pct": 9.656309853160247,
        "winner": "REP"
      },
      "55": {
        "dem_votes": 12374,
        "rep_votes": 25674,
        "other_votes": 1339,
        "total_votes": 39387,
        "dem_candidate": "Rochelle Mercedes Garza",
        "rep_candidate": "Ken Paxton",
        "margin": 13300,
        "margin_pct": 33.76748673420164,
        "winner": "REP"
      },
      "56": {
        "dem_votes": 17719,
        "rep_votes": 37128,
        "other_votes": 1739,
        "total_votes": 56586,
        "dem_candidate": "Rochelle Mercedes Garza",
        "rep_candidate": "Ken Paxton",
        "margin": 19409,
        "margin_pct": 34.30001205439581,
        "winner": "REP"
      },
      "57": {
        "dem_votes": 5960,
        "rep_votes": 24631,
        "other_votes": 3779,
        "total_votes": 34370,
        "dem_candidate": "Rochelle Mercedes Garza",
        "rep_candidate": "Ken Paxton",
        "margin": 18671,
        "margin_pct": 54.323537969159155,
        "winner": "REP"
      },
      "59": {
        "dem_votes": 4945,
        "rep_votes": 15396,
        "other_votes": 4627,
        "total_votes": 24968,
        "dem_candidate": "Rochelle Mercedes Garza",
        "rep_candidate": "Ken Paxton",
        "margin": 10451,
        "margin_pct": 41.8575776994553,
        "winner": "REP"
      },
      "60": {
        "dem_votes": 2770,
        "rep_votes": 19197,
        "other_votes": 483,
        "total_votes": 22450,
        "dem_candidate": "Rochelle Mercedes Garza",
        "rep_candidate": "Ken Paxton",
        "margin": 16427,
        "margin_pct": 73.17149220489978,
        "winner": "REP"
      },
      "62": {
        "dem_votes": 1791,
        "rep_votes": 9013,
        "other_votes": 313,
        "total_votes": 11117,
        "dem_candidate": "ROCHELLE MERCEDES GARZA",
        "rep_candidate": "KEN PAXTON",
        "margin": 7222,
        "margin_pct": 64.96356930826663,
        "winner": "REP"
      },
      "66": {
        "dem_votes": 31080,
        "rep_votes": 27596,
        "other_votes": 3323,
        "total_votes": 61999,
        "dem_candidate": "Rochelle Mercedes Garza",
        "rep_candidate": "Ken Paxton",
        "margin": -3484,
        "margin_pct": -5.619445474927015,
        "winner": "DEM"
      },
      "67": {
        "dem_votes": 35974,
        "rep_votes": 30676,
        "other_votes": 3785,
        "total_votes": 70435,
        "dem_candidate": "Rochelle Mercedes Garza",
        "rep_candidate": "Ken Paxton",
        "margin": -5298,
        "margin_pct": -7.521828636331369,
        "winner": "DEM"
      },
      "68": {
        "dem_votes": 3085,
        "rep_votes": 23030,
        "other_votes": 4499,
        "total_votes": 30614,
        "dem_candidate": "Rochelle Mercedes Garza",
        "rep_candidate": "Ken Paxton",
        "margin": 19945,
        "margin_pct": 65.14993140393284,
        "winner": "REP"
      },
      "69": {
        "dem_votes": 322,
        "rep_votes": 3246,
        "other_votes": 72,
        "total_votes": 3640,
        "dem_candidate": "Rochelle Mercedes Garza",
        "rep_candidate": "Ken Paxton",
        "margin": 2924,
        "margin_pct": 80.32967032967034,
        "winner": "REP"
      },
      "70": {
        "dem_votes": 35745,
        "rep_votes": 53647,
        "other_votes": 5069,
        "total_votes": 94461,
        "dem_candidate": "Rochelle Mercedes Garza",
        "rep_candidate": "Ken Paxton",
        "margin": 17902,
        "margin_pct": 18.951748311616736,
        "winner": "REP"
      },
      "71": {
        "dem_votes": 9665,
        "rep_votes": 31982,
        "other_votes": 1253,
        "total_votes": 42900,
        "dem_candidate": "Rochelle Mercedes Garza",
        "rep_candidate": "Ken Paxton",
        "margin": 22317,
        "margin_pct": 52.02097902097902,
        "winner": "REP"
      },
      "72": {
        "dem_votes": 1189,
        "rep_votes": 5687,
        "other_votes": 154,
        "total_votes": 7030,
        "dem_candidate": "Rochelle Mercedes Garza",
        "rep_candidate": "Ken Paxton",
        "margin": 4498,
        "margin_pct": 63.98293029871978,
        "winner": "REP"
      },
      "74": {
        "dem_votes": 4056,
        "rep_votes": 5969,
        "other_votes": 941,
        "total_votes": 10966,
        "dem_candidate": "Rochelle Mercedes Garza",
        "rep_candidate": "Ken Paxton",
        "margin": 1913,
        "margin_pct": 17.444829472916286,
        "winner": "REP"
      },
      "75": {
        "dem_votes": 19234,
        "rep_votes": 10780,
        "other_votes": 1947,
        "total_votes": 31961,
        "dem_candidate": "Rochelle Mercedes Garza",
        "rep_candidate": "Ken Paxton",
        "margin": -8454,
        "margin_pct": -26.45098714057758,
        "winner": "DEM"
      },
      "76": {
        "dem_votes": 17029,
        "rep_votes": 6318,
        "other_votes": 1617,
        "total_votes": 24963,
        "dem_candidate": "Rochelle Mercedes Garza",
        "rep_candidate": "Ken Paxton",
        "margin": -10711,
        "margin_pct": -42.907290713894675,
        "winner": "DEM"
      },
      "77": {
        "dem_votes": 18332,
        "rep_votes": 8812,
        "other_votes": 1940,
        "total_votes": 29085,
        "dem_candidate": "Rochelle Mercedes Garza",
        "rep_candidate": "Ken Paxton",
        "margin": -9520,
        "margin_pct": -32.731729688241515,
        "winner": "DEM"
      },
      "78": {
        "dem_votes": 23803,
        "rep_votes": 17760,
        "other_votes": 2633,
        "total_votes": 44196,
        "dem_candidate": "Rochelle Mercedes Garza",
        "rep_candidate": "Ken Paxton",
        "margin": -6043,
        "margin_pct": -13.673183093492625,
        "winner": "DEM"
      },
      "79": {
        "dem_votes": 21196,
        "rep_votes": 11246,
        "other_votes": 1691,
        "total_votes": 34133,
        "dem_candidate": "Rochelle Mercedes Garza",
        "rep_candidate": "Ken Paxton",
        "margin": -9950,
        "margin_pct": -29.150683195085154,
        "winner": "DEM"
      },
      "80": {
        "dem_votes": 2996,
        "rep_votes": 4634,
        "other_votes": 201,
        "total_votes": 7831,
        "dem_candidate": "Rochelle Mercedes Garza",
        "rep_candidate": "Ken Paxton",
        "margin": 1638,
        "margin_pct": 20.91686885455242,
        "winner": "REP"
      },
      "81": {
        "dem_votes": 6195,
        "rep_votes": 20829,
        "other_votes": 3120,
        "total_votes": 30144,
        "dem_candidate": "Rochelle Mercedes Garza",
        "rep_candidate": "Ken Paxton",
        "margin": 14634,
        "margin_pct": 48.546974522293,
        "winner": "REP"
      },
      "82": {
        "dem_votes": 7533,
        "rep_votes": 32829,
        "other_votes": 1984,
        "total_votes": 42346,
        "dem_candidate": "Rochelle Mercedes Garza",
        "rep_candidate": "Ken Paxton",
        "margin": 25296,
        "margin_pct": 59.73645680819912,
        "winner": "REP"
      },
      "83": {
        "dem_votes": 820,
        "rep_votes": 7327,
        "other_votes": 42120,
        "total_votes": 50267,
        "dem_candidate": "Rochelle Mercedes Garza",
        "rep_candidate": "Ken Paxton",
        "margin": 6507,
        "margin_pct": 12.944984299573372,
        "winner": "REP"
      },
      "84": {
        "dem_votes": 0,
        "rep_votes": 0,
        "other_votes": 37720,
        "total_votes": 37720,
        "dem_candidate": "",
        "rep_candidate": "",
        "margin": 0,
        "margin_pct": 0.0,
        "winner": "TIE"
      },
      "85": {
        "dem_votes": 770,
        "rep_votes": 824,
        "other_votes": 44,
        "total_votes": 1638,
        "dem_candidate": "Rochelle Mercedes Garza",
        "rep_candidate": "Ken Paxton",
        "margin": 54,
        "margin_pct": 3.296703296703297,
        "winner": "REP"
      },
      "86": {
        "dem_votes": 7116,
        "rep_votes": 34001,
        "other_votes": 971,
        "total_votes": 42088,
        "dem_candidate": "Rochelle Mercedes Garza",
        "rep_candidate": "Ken Paxton",
        "margin": 26885,
        "margin_pct": 63.878065006652726,
        "winner": "REP"
      },
      "87": {
        "dem_votes": 6521,
        "rep_votes": 23991,
        "other_votes": 820,
        "total_votes": 31332,
        "dem_candidate": "Rochelle Mercedes Garza",
        "rep_candidate": "Ken Paxton",
        "margin": 17470,
        "margin_pct": 55.75769181667305,
        "winner": "REP"
      },
      "88": {
        "dem_votes": 3798,
        "rep_votes": 22778,
        "other_votes": 2065,
        "total_votes": 28641,
        "dem_candidate": "Rochelle Mercedes Garza",
        "rep_candidate": "Ken Paxton",
        "margin": 18980,
        "margin_pct": 66.26863587165252,
        "winner": "REP"
      },
      "89": {
        "dem_votes": 30038,
        "rep_votes": 39958,
        "other_votes": 4235,
        "total_votes": 74231,
        "dem_candidate": "Rochelle Mercedes Garza",
        "rep_candidate": "Ken Paxton",
        "margin": 9920,
        "margin_pct": 13.363691018387296,
        "winner": "REP"
      },
      "90": {
        "dem_votes": 14907,
        "rep_votes": 5433,
        "other_votes": 605,
        "total_votes": 20945,
        "dem_candidate": "Rochelle Mercedes Garza",
        "rep_candidate": "Ken Paxton",
        "margin": -9474,
        "margin_pct": -45.23278160090481,
        "winner": "DEM"
      },
      "91": {
        "dem_votes": 19459,
        "rep_votes": 30714,
        "other_votes": 2085,
        "total_votes": 52258,
        "dem_candidate": "Rochelle Mercedes Garza",
        "rep_candidate": "Ken Paxton",
        "margin": 11255,
        "margin_pct": 21.537372268360823,
        "winner": "REP"
      },
      "92": {
        "dem_votes": 25996,
        "rep_votes": 27577,
        "other_votes": 2171,
        "total_votes": 55744,
        "dem_candidate": "Rochelle Mercedes Garza",
        "rep_candidate": "Ken Paxton",
        "margin": 1581,
        "margin_pct": 2.836118185434796,
        "winner": "REP"
      },
      "93": {
        "dem_votes": 25827,
        "rep_votes": 28598,
        "other_votes": 1972,
        "total_votes": 56397,
        "dem_candidate": "Rochelle Mercedes Garza",
        "rep_candidate": "Ken Paxton",
        "margin": 2770,
        "margin_pct": 4.912057097261264,
        "winner": "REP"
      },
      "94": {
        "dem_votes": 25497,
        "rep_votes": 27040,
        "other_votes": 1960,
        "total_votes": 54497,
        "dem_candidate": "Rochelle Mercedes Garza",
        "rep_candidate": "Ken Paxton",
        "margin": 1543,
        "margin_pct": 2.831348514597134,
        "winner": "REP"
      },
      "95": {
        "dem_votes": 26388,
        "rep_votes": 9018,
        "other_votes": 1112,
        "total_votes": 36518,
        "dem_candidate": "Rochelle Mercedes Garza",
        "rep_candidate": "Ken Paxton",
        "margin": -17370,
        "margin_pct": -47.56558409551454,
        "winner": "DEM"
      },
      "96": {
        "dem_votes": 28932,
        "rep_votes": 29804,
        "other_votes": 1865,
        "total_votes": 60601,
        "dem_candidate": "Rochelle Mercedes Garza",
        "rep_candidate": "Ken Paxton",
        "margin": 872,
        "margin_pct": 1.438920149832511,
        "winner": "REP"
      },
      "97": {
        "dem_votes": 29235,
        "rep_votes": 31424,
        "other_votes": 2473,
        "total_votes": 63132,
        "dem_candidate": "Rochelle Mercedes Garza",
        "rep_candidate": "Ken Paxton",
        "margin": 2189,
        "margin_pct": 3.467338275359564,
        "winner": "REP"
      },
      "98": {
        "dem_votes": 28388,
        "rep_votes": 51472,
        "other_votes": 3122,
        "total_votes": 82982,
        "dem_candidate": "Rochelle Mercedes Garza",
        "rep_candidate": "Ken Paxton",
        "margin": 23084,
        "margin_pct": 27.818081029620885,
        "winner": "REP"
      },
      "99": {
        "dem_votes": 21489,
        "rep_votes": 34120,
        "other_votes": 2194,
        "total_votes": 57802,
        "dem_candidate": "Rochelle Mercedes Garza",
        "rep_candidate": "Ken Paxton",
        "margin": 12631,
        "margin_pct": 21.851661268307517,
        "winner": "REP"
      },
      "100": {
        "dem_votes": 24696,
        "rep_votes": 6498,
        "other_votes": 1539,
        "total_votes": 32733,
        "dem_candidate": "Rochelle Mercedes Garza",
        "rep_candidate": "Ken Paxton",
        "margin": -18198,
        "margin_pct": -55.59531805912834,
        "winner": "DEM"
      },
      "101": {
        "dem_votes": 24173,
        "rep_votes": 11304,
        "other_votes": 954,
        "total_votes": 36431,
        "dem_candidate": "Rochelle Mercedes Garza",
        "rep_candidate": "Ken Paxton",
        "margin": -12869,
        "margin_pct": -35.3243117125525,
        "winner": "DEM"
      },
      "102": {
        "dem_votes": 20099,
        "rep_votes": 15079,
        "other_votes": 1911,
        "total_votes": 37089,
        "dem_candidate": "Rochelle Mercedes Garza",
        "rep_candidate": "Ken Paxton",
        "margin": -5020,
        "margin_pct": -13.53501038043625,
        "winner": "DEM"
      },
      "103": {
        "dem_votes": 19902,
        "rep_votes": 5751,
        "other_votes": 1154,
        "total_votes": 26807,
        "dem_candidate": "Rochelle Mercedes Garza",
        "rep_candidate": "Ken Paxton",
        "margin": -14151,
        "margin_pct": -52.788450777781925,
        "winner": "DEM"
      },
      "104": {
        "dem_votes": 19224,
        "rep_votes": 6018,
        "other_votes": 1257,
        "total_votes": 26499,
        "dem_candidate": "Rochelle Mercedes Garza",
        "rep_candidate": "Ken Paxton",
        "margin": -13206,
        "margin_pct": -49.83584286199479,
        "winner": "DEM"
      },
      "105": {
        "dem_votes": 19529,
        "rep_votes": 15385,
        "other_votes": 1929,
        "total_votes": 36843,
        "dem_candidate": "Rochelle Mercedes Garza",
        "rep_candidate": "Ken Paxton",
        "margin": -4144,
        "margin_pct": -11.247726840919578,
        "winner": "DEM"
      },
      "107": {
        "dem_votes": 16638,
        "rep_votes": 11692,
        "other_votes": 1432,
        "total_votes": 29762,
        "dem_candidate": "Rochelle Mercedes Garza",
        "rep_candidate": "Ken Paxton",
        "margin": -4946,
        "margin_pct": -16.618899839298816,
        "winner": "DEM"
      },
      "108": {
        "dem_votes": 21418,
        "rep_votes": 22320,
        "other_votes": 2516,
        "total_votes": 46254,
        "dem_candidate": "Rochelle Mercedes Garza",
        "rep_candidate": "Ken Paxton",
        "margin": 902,
        "margin_pct": 1.9501016128334845,
        "winner": "REP"
      },
      "109": {
        "dem_votes": 38343,
        "rep_votes": 8043,
        "other_votes": 2073,
        "total_votes": 48459,
        "dem_candidate": "Rochelle Mercedes Garza",
        "rep_candidate": "Ken Paxton",
        "margin": -30300,
        "margin_pct": -62.52688361258234,
        "winner": "DEM"
      },
      "110": {
        "dem_votes": 17218,
        "rep_votes": 2869,
        "other_votes": 943,
        "total_votes": 21030,
        "dem_candidate": "Rochelle Mercedes Garza",
        "rep_candidate": "Ken Paxton",
        "margin": -14349,
        "margin_pct": -68.23109843081312,
        "winner": "DEM"
      },
      "111": {
        "dem_votes": 33753,
        "rep_votes": 8887,
        "other_votes": 2054,
        "total_votes": 44694,
        "dem_candidate": "Rochelle Mercedes Garza",
        "rep_candidate": "Ken Paxton",
        "margin": -24866,
        "margin_pct": -55.63627457110593,
        "winner": "DEM"
      },
      "112": {
        "dem_votes": 9300,
        "rep_votes": 6474,
        "other_votes": 874,
        "total_votes": 16648,
        "dem_candidate": "Rochelle Mercedes Garza",
        "rep_candidate": "Ken Paxton",
        "margin": -2826,
        "margin_pct": -16.97501201345507,
        "winner": "DEM"
      },
      "113": {
        "dem_votes": 10024,
        "rep_votes": 7458,
        "other_votes": 782,
        "total_votes": 18264,
        "dem_candidate": "Rochelle Mercedes Garza",
        "rep_candidate": "Ken Paxton",
        "margin": -2566,
        "margin_pct": -14.049496276828735,
        "winner": "DEM"
      },
      "114": {
        "dem_votes": 21999,
        "rep_votes": 16465,
        "other_votes": 2210,
        "total_votes": 40674,
        "dem_candidate": "Rochelle Mercedes Garza",
        "rep_candidate": "Ken Paxton",
        "margin": -5534,
        "margin_pct": -13.605743226631265,
        "winner": "DEM"
      },
      "115": {
        "dem_votes": 26319,
        "rep_votes": 18978,
        "other_votes": 2144,
        "total_votes": 47441,
        "dem_candidate": "Rochelle Mercedes Garza",
        "rep_candidate": "Ken Paxton",
        "margin": -7341,
        "margin_pct": -15.473957125692966,
        "winner": "DEM"
      },
      "116": {
        "dem_votes": 26943,
        "rep_votes": 13535,
        "other_votes": 2036,
        "total_votes": 42514,
        "dem_candidate": "Rochelle Mercedes Garza",
        "rep_candidate": "Ken Paxton",
        "margin": -13408,
        "margin_pct": -31.538036436089474,
        "winner": "DEM"
      },
      "117": {
        "dem_votes": 33601,
        "rep_votes": 25215,
        "other_votes": 2710,
        "total_votes": 61526,
        "dem_candidate": "Rochelle Mercedes Garza",
        "rep_candidate": "Ken Paxton",
        "margin": -8386,
        "margin_pct": -13.63000434229446,
        "winner": "DEM"
      },
      "118": {
        "dem_votes": 20732,
        "rep_votes": 16685,
        "other_votes": 1997,
        "total_votes": 39414,
        "dem_candidate": "Rochelle Mercedes Garza",
        "rep_candidate": "Ken Paxton",
        "margin": -4047,
        "margin_pct": -10.267896796697656,
        "winner": "DEM"
      },
      "119": {
        "dem_votes": 25199,
        "rep_votes": 15658,
        "other_votes": 2147,
        "total_votes": 43004,
        "dem_candidate": "Rochelle Mercedes Garza",
        "rep_candidate": "Ken Paxton",
        "margin": -9541,
        "margin_pct": -22.18630825039531,
        "winner": "DEM"
      },
      "120": {
        "dem_votes": 24406,
        "rep_votes": 12507,
        "other_votes": 2025,
        "total_votes": 38938,
        "dem_candidate": "Rochelle Mercedes Garza",
        "rep_candidate": "Ken Paxton",
        "margin": -11899,
        "margin_pct": -30.558925642324787,
        "winner": "DEM"
      },
      "121": {
        "dem_votes": 35564,
        "rep_votes": 33434,
        "other_votes": 3429,
        "total_votes": 72427,
        "dem_candidate": "Rochelle Mercedes Garza",
        "rep_candidate": "Ken Paxton",
        "margin": -2130,
        "margin_pct": -2.940892208706698,
        "winner": "DEM"
      },
      "122": {
        "dem_votes": 39364,
        "rep_votes": 48433,
        "other_votes": 3627,
        "total_votes": 91424,
        "dem_candidate": "Rochelle Mercedes Garza",
        "rep_candidate": "Ken Paxton",
        "margin": 9069,
        "margin_pct": 9.919714735736788,
        "winner": "REP"
      },
      "123": {
        "dem_votes": 29602,
        "rep_votes": 12742,
        "other_votes": 2295,
        "total_votes": 44639,
        "dem_candidate": "Rochelle Mercedes Garza",
        "rep_candidate": "Ken Paxton",
        "margin": -16860,
        "margin_pct": -37.769418272188254,
        "winner": "DEM"
      },
      "124": {
        "dem_votes": 26190,
        "rep_votes": 13638,
        "other_votes": 1983,
        "total_votes": 41811,
        "dem_candidate": "Rochelle Mercedes Garza",
        "rep_candidate": "Ken Paxton",
        "margin": -12552,
        "margin_pct": -30.02082486269831,
        "winner": "DEM"
      },
      "125": {
        "dem_votes": 23743,
        "rep_votes": 13183,
        "other_votes": 1899,
        "total_votes": 38825,
        "dem_candidate": "Rochelle Mercedes Garza",
        "rep_candidate": "Ken Paxton",
        "margin": -10560,
        "margin_pct": -27.19896973599485,
        "winner": "DEM"
      },
      "136": {
        "dem_votes": 21703,
        "rep_votes": 14233,
        "other_votes": 2603,
        "total_votes": 38539,
        "dem_candidate": "Rochelle Mercedes Garza",
        "rep_candidate": "Ken Paxton",
        "margin": -7470,
        "margin_pct": -19.382962713095825,
        "winner": "DEM"
      }
    }
  }
}